FoxitPDFSDKPython3/__init__.py
FoxitPDFSDKPython3/_fsdk.pyd
FoxitPDFSDKPython3/fsdk.py
FoxitPDFSDKPython3-11.0.0.dist-info/METADATA
FoxitPDFSDKPython3-11.0.0.dist-info/WHEEL
FoxitPDFSDKPython3-11.0.0.dist-info/legal.txt
FoxitPDFSDKPython3-11.0.0.dist-info/top_level.txt
FoxitPDFSDKPython3-11.0.0.dist-info/RECORD
