Metadata-Version: 2.1
Name: FoxitPDFSDKPython3
Version: 11.0.0
Summary: Foxit PDF SDK For Python3
Home-page: https://developers.foxit.com
Author: Foxit Software Inc.
Author-email: support@foxitsoftware.com
License: Other/Proprietary License (Commercial)
Keywords: PDF SDK,PDF Library,PDF render,PDF view,PDF print,PDF Edit,PDF convert
Platform: UNKNOWN
Classifier: Development Status :: 5 - Production/Stable
Classifier: Intended Audience :: Developers
Classifier: Operating System :: Microsoft :: Windows
Classifier: Operating System :: POSIX
Classifier: Operating System :: Unix
Classifier: Operating System :: MacOS
Classifier: Programming Language :: Python
Classifier: Programming Language :: Python :: 3 :: Only
Classifier: Programming Language :: Python :: 3
Classifier: Programming Language :: Python :: 3.6
Classifier: Programming Language :: Python :: 3.7
Classifier: Programming Language :: Python :: 3.8
Classifier: Programming Language :: Python :: 3.9
Classifier: Programming Language :: Python :: 3.10
Classifier: Programming Language :: Python :: 3.11
Classifier: Programming Language :: Python :: Implementation :: CPython
Classifier: Topic :: Software Development
Requires-Python: >=3.6, <4
